ares_tagger/__init__.py
ares_tagger/validator.py
tag_db_verification-0.5.9.dist-info/METADATA
tag_db_verification-0.5.9.dist-info/WHEEL
tag_db_verification-0.5.9.dist-info/top_level.txt
tag_db_verification-0.5.9.dist-info/RECORD
