Metadata-Version: 2.1
Name: tag-db-verification
Version: 0.5.9
Requires-Dist: runcmd
Requires-Dist: values
